phinix/__init__.py
phinix/exceptions.py
phinix/main.py
phinix-0.0.8.dist-info/METADATA
phinix-0.0.8.dist-info/WHEEL
phinix-0.0.8.dist-info/top_level.txt
phinix-0.0.8.dist-info/RECORD
